datapluck/__init__.py
datapluck/credentials.json
datapluck/google_auth.py
datapluck/main.py
datapluck/vector.py
datapluck-0.1.10.dist-info/LICENSE
datapluck-0.1.10.dist-info/METADATA
datapluck-0.1.10.dist-info/WHEEL
datapluck-0.1.10.dist-info/entry_points.txt
datapluck-0.1.10.dist-info/top_level.txt
datapluck-0.1.10.dist-info/RECORD
