Metadata-Version: 2.1
Name: datapluck
Version: 0.1.10
Summary: Export & import Hugging Face datasets to spreadsheets and various file formats.
Author: Omar Kamali
Author-email: pypi@datapluck.org
Keywords: huggingface datasets export csv json parquet tsv jsonl google-sheets spreadsheets google microsoft excel xls xlsx
Classifier: Development Status :: 3 - Alpha
Classifier: Intended Audience :: Developers
Classifier: Intended Audience :: Science/Research
Classifier: Programming Language :: Python :: 3
Classifier: Programming Language :: Python :: 3 :: Only
Classifier: Programming Language :: Python :: 3.8
Classifier: Operating System :: OS Independent
Classifier: Topic :: Software Development :: Libraries :: Python Modules
Classifier: Topic :: Utilities
Requires-Python: >=3.8
License-File: LICENSE
Requires-Dist: pandas
Requires-Dist: datasets
Requires-Dist: pyarrow
Requires-Dist: openpyxl
Requires-Dist: pysqlite3
Requires-Dist: google-auth
Requires-Dist: google-auth-oauthlib
Requires-Dist: google-api-python-client
